pylovelace/__init__.py
pylovelace/__main__.py
pylovelace/protect.py
pylovelace-2023.2.1.dist-info/LICENSE
pylovelace-2023.2.1.dist-info/METADATA
pylovelace-2023.2.1.dist-info/WHEEL
pylovelace-2023.2.1.dist-info/entry_points.txt
pylovelace-2023.2.1.dist-info/top_level.txt
pylovelace-2023.2.1.dist-info/RECORD
