Metadata-Version: 2.1
Name: pylovelace
Version: 2023.2.1
Summary: Python code protection/obfuscation tool
Home-page: https://github.com/pylovelace/pylovelace
Author: nshout
Keywords: obfuscate obfuscation distribute production tool
Classifier: Development Status :: 5 - Production/Stable
Classifier: Intended Audience :: Developers
Classifier: Topic :: Utilities
Classifier: Topic :: Security
Classifier: Programming Language :: Python :: 3.10
Classifier: Programming Language :: Python :: 3.11
Classifier: Programming Language :: Python :: 3.12
Classifier: Operating System :: Microsoft :: Windows :: Windows 10
Classifier: Operating System :: Microsoft :: Windows :: Windows 11
Classifier: Operating System :: POSIX :: Linux
Requires-Python: >=3.10, <3.13
License-File: LICENSE
Requires-Dist: pylovelace.kernel (>=2023.3.0)
